odoo10_addon_intrastat_product-10.0.1.3.1-nspkg.pth
odoo/addons/intrastat_product/README.rst
odoo/addons/intrastat_product/__init__.py
odoo/addons/intrastat_product/__manifest__.py
odoo/addons/intrastat_product/data/intrastat_transport_mode.xml
odoo/addons/intrastat_product/data/intrastat_unit.xml
odoo/addons/intrastat_product/demo/intrastat_demo.xml
odoo/addons/intrastat_product/i18n/intrastat_product.pot
odoo/addons/intrastat_product/models/__init__.py
odoo/addons/intrastat_product/models/account_config_settings.py
odoo/addons/intrastat_product/models/account_invoice.py
odoo/addons/intrastat_product/models/hs_code.py
odoo/addons/intrastat_product/models/intrastat_product_declaration.py
odoo/addons/intrastat_product/models/intrastat_region.py
odoo/addons/intrastat_product/models/intrastat_transaction.py
odoo/addons/intrastat_product/models/intrastat_transport_mode.py
odoo/addons/intrastat_product/models/intrastat_unit.py
odoo/addons/intrastat_product/models/res_company.py
odoo/addons/intrastat_product/models/sale_order.py
odoo/addons/intrastat_product/models/stock_warehouse.py
odoo/addons/intrastat_product/report/__init__.py
odoo/addons/intrastat_product/report/intrastat_product_report_xls.py
odoo/addons/intrastat_product/security/intrastat_security.xml
odoo/addons/intrastat_product/security/ir.model.access.csv
odoo/addons/intrastat_product/static/description/icon.png
odoo/addons/intrastat_product/views/account_config_settings.xml
odoo/addons/intrastat_product/views/account_invoice.xml
odoo/addons/intrastat_product/views/hs_code.xml
odoo/addons/intrastat_product/views/intrastat_product_declaration.xml
odoo/addons/intrastat_product/views/intrastat_region.xml
odoo/addons/intrastat_product/views/intrastat_transaction.xml
odoo/addons/intrastat_product/views/intrastat_transport_mode.xml
odoo/addons/intrastat_product/views/intrastat_unit.xml
odoo/addons/intrastat_product/views/sale_order.xml
odoo/addons/intrastat_product/views/stock_warehouse.xml
odoo10_addon_intrastat_product-10.0.1.3.1.dist-info/METADATA
odoo10_addon_intrastat_product-10.0.1.3.1.dist-info/WHEEL
odoo10_addon_intrastat_product-10.0.1.3.1.dist-info/namespace_packages.txt
odoo10_addon_intrastat_product-10.0.1.3.1.dist-info/top_level.txt
odoo10_addon_intrastat_product-10.0.1.3.1.dist-info/RECORD
